{
  "meta": {
    "generated_at": "2026-01-29T20:54:32",
    "model_type": "char_cnn",
    "label_convention": {
      "0": "Malicious",
      "1": "Benign"
    },
    "threshold": 0.5,
    "data": {
      "white_list": "data\\white_list.csv",
      "block_list": "data\\block_list.csv",
      "train_size": 56000,
      "test_size": 24000,
      "test_split_ratio": 0.3,
      "seed": 42
    },
    "preprocess": {
      "max_len": 200,
      "vocab_size": 92,
      "max_vocab_size": 0,
      "embed_dim": 64
    },
    "train": {
      "epochs": 3,
      "batch_size": 256,
      "lr": 0.001
    }
  },
  "metrics": {
    "accuracy": 0.998125,
    "precision": 0.9970067348465952,
    "recall": 0.99925,
    "f1": 0.9981271070046198,
    "auc": 0.9995530347222225,
    "training_time_sec": 40.46583437919617,
    "inference_time_sec": 2.202012777328491,
    "latency_per_url_ms": 0.09175053238868713,
    "confusion_matrix": {
      "labels": [
        0,
        1
      ],
      "matrix": [
        [
          11964,
          36
        ],
        [
          9,
          11991
        ]
      ]
    }
  }
}